simple_calculator/__init__.py
simple_calculator/_version.py
simple_calculator/cli.py
simple_calculator/core.py
kennys_simple_calculator-0.1.0.dist-info/METADATA
kennys_simple_calculator-0.1.0.dist-info/WHEEL
kennys_simple_calculator-0.1.0.dist-info/entry_points.txt
kennys_simple_calculator-0.1.0.dist-info/licenses/LICENSE
kennys_simple_calculator-0.1.0.dist-info/RECORD
